mvic/__init__.py
mvic/thumbnail.py
mvic/video.py
mvic-0.1.3.dist-info/METADATA
mvic-0.1.3.dist-info/WHEEL
mvic-0.1.3.dist-info/top_level.txt
mvic-0.1.3.dist-info/RECORD
