Metadata-Version: 2.1
Name: mvic
Version: 0.1.3
Summary: A basic python script to make music video images using pillow.
Home-page: UNKNOWN
Author: JustCow
Author-email: <justcow@pm.me>
License: UNKNOWN
Keywords: python,video,image creator,justcow
Platform: UNKNOWN
Classifier: Programming Language :: Python :: 3
Classifier: Operating System :: Unix
Classifier: Operating System :: MacOS :: MacOS X
Classifier: Operating System :: Microsoft :: Windows
Requires-Dist: pillow
